AthenaServer/__init__.py
AthenaServer/_info/__init__.py
AthenaServer/_info/_v.py
AthenaServer/data/__init__.py
AthenaServer/data/output_texts.py
AthenaServer/data/return_codes.py
AthenaServer/functions/__init__.py
AthenaServer/functions/output_callbacks.py
AthenaServer/models/__init__.py
AthenaServer/models/athena_server.py
AthenaServer/models/athena_server_data_handler.py
AthenaServer/models/athena_server_protocol.py
AthenaServer/models/athena_server_response.py
AthenaServer/models/athena_server_pages/__init__.py
AthenaServer/models/athena_server_pages/athena_server_page.py
AthenaServer/models/athena_server_pages/athena_server_page_logic.py
AthenaServer/models/athena_server_pages/athena_server_page_structure.py
AthenaServer/models/outputs/__init__.py
AthenaServer/models/outputs/output.py
AthenaServer/models/outputs/output_client.py
AthenaServer/models/outputs/output_console.py
AthenaServer-0.1.0.dist-info/METADATA
AthenaServer-0.1.0.dist-info/WHEEL
AthenaServer-0.1.0.dist-info/top_level.txt
AthenaServer-0.1.0.dist-info/RECORD
