Metadata-Version: 2.1
Name: AthenaServer
Version: 0.1.0
Summary: A general server system for Directive Athena Applications
Home-page: https://github.com/DirectiveAthena/AthenaServer
Author: Andreas Sas
Author-email: 
License: GPLv3
Project-URL: Bug Tracker, https://github.com/DirectiveAthena/AthenaServer/issues
Requires-Python: >=3.10
Requires-Dist: AthenaColor (~=6.0.2)
Requires-Dist: AthenaLib (~=1.3.0)
